setup.py
pmst/__init__.py
pmst.egg-info/PKG-INFO
pmst.egg-info/SOURCES.txt
pmst.egg-info/dependency_links.txt
pmst.egg-info/top_level.txt
pmst.egg-info/zip-safe