Metadata-Version: 1.0
Name: pmst
Version: 0.1
Summary: Polarized microscope simulation tool.
Home-page: https://github.com/talonchandler/pmst
Author: Talon Chandler
Author-email: talonchandler@uchicago.edu
License: MIT
Platform: UNKNOWN
